{"id":"gen9vgc2026regi-2568576365","format":"[Gen 9] VGC 2026 Reg I","players":["hfyssgtslaaa","TreeHuger03"],"log":"|j|\u2606hfyssgtslaaa\n|j|\u2606TreeHuger03\n|t:|1774599226\n|gametype|doubles\n|player|p1|hfyssgtslaaa|may-masters2|1287\n|player|p2|TreeHuger03|102|1365\n|gen|9\n|tier|[Gen 9] VGC 2026 Reg I\n|rated|\n|rule|Species Clause: Limit one of each Pok\u00e9mon\n|rule|Item Clause: Limit 1 of each item\n|clearpoke\n|poke|p1|Raging Bolt, L50|\n|poke|p1|Chien-Pao, L50|\n|poke|p1|Calyrex-Shadow, L50|\n|poke|p1|Rillaboom, L50, M|\n|poke|p1|Amoonguss, L50, M|\n|poke|p1|Zamazenta-*, L50|\n|poke|p2|Necrozma-Dawn-Wings, L50|\n|poke|p2|Calyrex-Ice, L50|\n|poke|p2|Incineroar, L50, M|\n|poke|p2|Amoonguss, L50, F|\n|poke|p2|Indeedee-F, L50, F|\n|poke|p2|Empoleon, L50, M|\n|teampreview|4\n|inactive|Battle timer is ON: inactive players will automatically lose when time's up. (requested by TreeHuger03)\n|inactive|hfyssgtslaaa also wants the timer to be on.\n|inactive|hfyssgtslaaa has 60 seconds left.\n|\n|t:|1774599259\n|teamsize|p1|4\n|teamsize|p2|4\n|start\n|switch|p1a: Calyrex|Calyrex-Shadow, L50|100/100\n|switch|p1b: Zamazenta|Zamazenta-Crowned, L50|100/100\n|switch|p2a: Necrozma|Necrozma-Dawn-Wings, L50|100/100\n|switch|p2b: Indeedee|Indeedee-F, L50, F|100/100\n|-ability|p1a: Calyrex|As One\n|-ability|p1a: Calyrex|Unnerve\n|-ability|p1b: Zamazenta|Dauntless Shield|boost\n|-boost|p1b: Zamazenta|def|1\n|-fieldstart|move: Psychic Terrain|[from] ability: Psychic Surge|[of] p2b: Indeedee\n|turn|1\n|inactive|hfyssgtslaaa has 30 seconds left.\n|inactive|hfyssgtslaaa has 20 seconds left.\n|\n|t:|1774599295\n|-terastallize|p2a: Necrozma|Normal\n|move|p1b: Zamazenta|Wide Guard|p1b: Zamazenta\n|-singleturn|p1b: Zamazenta|Wide Guard\n|move|p1a: Calyrex|Astral Barrage|p2a: Necrozma|[spread] \n|-immune|p2a: Necrozma\n|-immune|p2b: Indeedee\n|move|p2a: Necrozma|Moongeist Beam|p1a: Calyrex\n|-supereffective|p1a: Calyrex\n|-enditem|p1a: Calyrex|Focus Sash\n|-damage|p1a: Calyrex|1/100\n|move|p2b: Indeedee|Trick Room|p2b: Indeedee\n|-fieldstart|move: Trick Room|[of] p2b: Indeedee\n|\n|upkeep\n|turn|2\n|inactive|TreeHuger03 has 30 seconds left.\n|\n|t:|1774599321\n|move|p1a: Calyrex|Protect|p1a: Calyrex\n|-singleturn|p1a: Calyrex|Protect\n|move|p2a: Necrozma|Moongeist Beam|p1b: Zamazenta\n|-crit|p1b: Zamazenta\n|-damage|p1b: Zamazenta|34/100\n|move|p2b: Indeedee|Dazzling Gleam|p1a: Calyrex|[spread] p1b\n|-activate|p1a: Calyrex|move: Protect\n|-damage|p1b: Zamazenta|24/100\n|move|p1b: Zamazenta|Body Press|p2a: Necrozma\n|-supereffective|p2a: Necrozma\n|-damage|p2a: Necrozma|9/100\n|\n|upkeep\n|turn|3\n|-message|hfyssgtslaaa forfeited.\n|\n|win|TreeHuger03\n|raw|hfyssgtslaaa's rating: 1287 &rarr; <strong>1268</strong><br />(-19 for losing)\n|raw|TreeHuger03's rating: 1365 &rarr; <strong>1381</strong><br />(+16 for winning)\n|l|\u2606hfyssgtslaaa\n|player|p1|\n|l|\u2606TreeHuger03\n|player|p2|\n","uploadtime":1774599513,"views":13,"formatid":"gen9vgc2026regi","rating":1268,"private":0,"password":null}