{"id":"gen9vgc2026regi-2563942797","format":"[Gen 9] VGC 2026 Reg I","players":["TheManOfSausage","ImseSixten"],"log":"|j|\u2606TheManOfSausage\n|j|\u2606ImseSixten\n|t:|1774089111\n|gametype|doubles\n|player|p1|TheManOfSausage|miku-water|1458\n|player|p2|ImseSixten|arezu|1393\n|gen|9\n|tier|[Gen 9] VGC 2026 Reg I\n|rated|\n|rule|Species Clause: Limit one of each Pok\u00e9mon\n|rule|Item Clause: Limit 1 of each item\n|clearpoke\n|poke|p1|Calyrex-Ice, L50|\n|poke|p1|Kyogre, L50|\n|poke|p1|Rillaboom, L50, M|\n|poke|p1|Urshifu-*, L50, M|\n|poke|p1|Roaring Moon, L50|\n|poke|p1|Landorus, L50, M|\n|poke|p2|Calyrex-Shadow, L50|\n|poke|p2|Indeedee-F, L50, F|\n|poke|p2|Zamazenta-*, L50|\n|poke|p2|Regidrago, L50|\n|poke|p2|Tornadus, L50, M|\n|poke|p2|Urshifu-*, L50, M|\n|teampreview|4\n|inactive|Battle timer is ON: inactive players will automatically lose when time's up. (requested by ImseSixten)\nTheManOfSausage has agreed to open team sheets.\n|inactive|ImseSixten has 60 seconds left.\n|\n|t:|1774089152\n|teamsize|p1|4\n|teamsize|p2|4\n|start\n|switch|p1a: Rillaboom|Rillaboom, L50, M|100/100\n|switch|p1b: Ogurin|Calyrex-Ice, L50|100/100\n|switch|p2a: Regidrago|Regidrago, L50|100/100\n|switch|p2b: Tornadus|Tornadus, L50, M|100/100\n|-ability|p1b: Ogurin|As One\n|-ability|p1b: Ogurin|Unnerve\n|-fieldstart|move: Grassy Terrain|[from] ability: Grassy Surge|[of] p1a: Rillaboom\n|turn|1\n|\n|t:|1774089162\n|switch|p2b: Indeedee|Indeedee-F, L50, F|100/100\n|-fieldstart|move: Psychic Terrain|[from] ability: Psychic Surge|[of] p2b: Indeedee\n|move|p2a: Regidrago|Dragon Energy|p1a: Rillaboom|[spread] p1a,p1b\n|-damage|p1a: Rillaboom|37/100\n|-damage|p1b: Ogurin|47/100\n|move|p1a: Rillaboom|U-turn|p2b: Indeedee\n|-supereffective|p2b: Indeedee\n|-damage|p2b: Indeedee|56/100\n|-damage|p1a: Rillaboom|21/100|[from] item: Rocky Helmet|[of] p2b: Indeedee\n|\n|t:|1774089167\n|switch|p1a: Kyogre|Kyogre, L50|100/100|[from] U-turn\n|-weather|RainDance|[from] ability: Drizzle|[of] p1a: Kyogre\n|move|p1b: Ogurin|Trick Room|p1b: Ogurin\n|-fieldstart|move: Trick Room|[of] p1b: Ogurin\n|\n|-weather|RainDance|[upkeep]\n|-heal|p1b: Ogurin|52/100|[from] item: Leftovers\n|upkeep\n|turn|2\n|\n|t:|1774089187\n|switch|p2b: Tornadus|Tornadus, L50, M|100/100\n|-terastallize|p2a: Regidrago|Ghost\n|move|p1b: Ogurin|Glacial Lance|p2a: Regidrago|[spread] p2a,p2b\n|-supereffective|p2b: Tornadus\n|-damage|p2a: Regidrago|37/100\n|-damage|p2b: Tornadus|0 fnt\n|faint|p2b: Tornadus\n|-ability|p1b: Ogurin|Chilling Neigh|boost\n|-boost|p1b: Ogurin|atk|1\n|move|p1a: Kyogre|Water Spout|p2a: Regidrago\n|-crit|p2a: Regidrago\n|-damage|p2a: Regidrago|0 fnt\n|faint|p2a: Regidrago\n|\n|-weather|RainDance|[upkeep]\n|-heal|p1b: Ogurin|58/100|[from] item: Leftovers\n|upkeep\n|\n|t:|1774089197\n|switch|p2a: Calyrex|Calyrex-Shadow, L50|100/100\n|switch|p2b: Indeedee|Indeedee-F, L50, F|56/100\n|-ability|p2a: Calyrex|As One\n|-ability|p2a: Calyrex|Unnerve\n|turn|3\n|\n|t:|1774089200\n|move|p2a: Calyrex|Protect|p2a: Calyrex\n|-singleturn|p2a: Calyrex|Protect\n|move|p1b: Ogurin|Glacial Lance|p2b: Indeedee|[spread] p2b\n|-activate|p2a: Calyrex|move: Protect\n|-damage|p2b: Indeedee|0 fnt\n|faint|p2b: Indeedee\n|-ability|p1b: Ogurin|Chilling Neigh|boost\n|-boost|p1b: Ogurin|atk|1\n|move|p1a: Kyogre|Water Spout|p2a: Calyrex\n|-activate|p2a: Calyrex|move: Protect\n|\n|-weather|RainDance|[upkeep]\n|-heal|p1b: Ogurin|64/100|[from] item: Leftovers\n|upkeep\n|turn|4\n|\n|t:|1774089204\n|move|p2a: Calyrex|Protect||[still]\n|-fail|p2a: Calyrex\n|move|p1b: Ogurin|Glacial Lance|p2a: Calyrex\n|-damage|p2a: Calyrex|0 fnt\n|faint|p2a: Calyrex\n|\n|win|TheManOfSausage\n|raw|TheManOfSausage's rating: 1458 &rarr; <strong>1474</strong><br />(+16 for winning)\n|raw|ImseSixten's rating: 1393 &rarr; <strong>1377</strong><br />(-16 for losing)\n|l|\u2606ImseSixten\n|player|p2|\n|l|\u2606TheManOfSausage\n|player|p1|\n","uploadtime":1774089461,"views":15,"formatid":"gen9vgc2026regi","rating":1377,"private":0,"password":null}