{"id":"gen9vgc2026regi-2546221541","format":"[Gen 9] VGC 2026 Reg I","players":["fu1111111","kojimuranishi"],"log":"|j|\u2606fu1111111\n|j|\u2606kojimuranishi\n|t:|1771944565\n|gametype|doubles\n|player|p1|fu1111111|2|1319\n|player|p2|kojimuranishi|266|1553\n|gen|9\n|tier|[Gen 9] VGC 2026 Reg I\n|rated|\n|rule|Species Clause: Limit one of each Pok\u00e9mon\n|rule|Item Clause: Limit 1 of each item\n|clearpoke\n|poke|p1|Whimsicott, L50, F|\n|poke|p1|Flutter Mane, L50|\n|poke|p1|Calyrex-Shadow, L50|\n|poke|p1|Raichu, L50, M|\n|poke|p1|Kyogre, L50|\n|poke|p1|Urshifu-*, L50, F|\n|poke|p2|Raging Bolt, L50|\n|poke|p2|Calyrex-Ice, L50|\n|poke|p2|Kyogre, L50|\n|poke|p2|Indeedee-F, L50, F|\n|poke|p2|Ursaluna, L50, M|\n|poke|p2|Urshifu-*, L50, F|\n|teampreview|4\n|inactive|Battle timer is ON: inactive players will automatically lose when time's up. (requested by kojimuranishi)\n|\n|t:|1771944600\n|teamsize|p1|4\n|teamsize|p2|4\n|start\n|switch|p1a: Raichu|Raichu, L50, M|100/100\n|switch|p1b: Urshifu|Urshifu, L50, F|100/100\n|switch|p2a: Raging Bolt|Raging Bolt, L50|100/100\n|switch|p2b: Calyrex|Calyrex-Ice, L50|100/100\n|-ability|p2b: Calyrex|As One\n|-ability|p2b: Calyrex|Unnerve\n|-enditem|p2a: Raging Bolt|Booster Energy\n|-activate|p2a: Raging Bolt|ability: Protosynthesis|[fromitem]\n|-start|p2a: Raging Bolt|protosynthesisspa\n|turn|1\n|inactive|fu1111111 has 30 seconds left.\n|inactive|fu1111111 has 20 seconds left.\n|inactive|fu1111111 has 15 seconds left.\n|inactive|fu1111111 has 10 seconds left.\n|l|\u2606kojimuranishi\n|inactive|kojimuranishi disconnected and has a minute to reconnect!\n|player|p2|\n|\n|t:|1771944648\n|-terastallize|p2b: Calyrex|Fairy\n|move|p1a: Raichu|Fake Out|p2b: Calyrex\n|-damage|p2b: Calyrex|96/100\n|move|p1b: Urshifu|Wicked Blow|p2b: Calyrex\n|-resisted|p2b: Calyrex\n|-crit|p2b: Calyrex\n|-damage|p2b: Calyrex|75/100\n|move|p2a: Raging Bolt|Draco Meteor|p1a: Raichu|[miss]\n|-miss|p2a: Raging Bolt|p1a: Raichu\n|cant|p2b: Calyrex|flinch\n|\n|-heal|p2b: Calyrex|81/100|[from] item: Leftovers\n|upkeep\n|turn|2\n|inactive|fu1111111 has 30 seconds left.\n|inactive|kojimuranishi has 30 seconds left.\n|inactive|kojimuranishi has 20 seconds left.\n|inactive|kojimuranishi has 15 seconds left.\n|inactive|kojimuranishi has 10 seconds left.\n|inactive|kojimuranishi has 5 seconds left.\n|-message|kojimuranishi lost due to inactivity.\n|\n|win|fu1111111\n|raw|fu1111111's rating: 1319 &rarr; <strong>1351</strong><br />(+32 for winning)\n|raw|kojimuranishi's rating: 1553 &rarr; <strong>1521</strong><br />(-32 for losing)\n|l|\u2606fu1111111\n|player|p1|\n|j|\u2606kojimuranishi\n|player|p2|kojimuranishi|266|\n|l|\u2606kojimuranishi\n|player|p2|\n","uploadtime":1771944875,"views":15,"formatid":"gen9vgc2026regi","rating":1351,"private":0,"password":null}