{"id":"gen9vgc2026regi-2578831042","format":"[Gen 9] VGC 2026 Reg I","players":["San gerger","navinsachump"],"log":"|j|\u2606San gerger\n|j|\u2606navinsachump\n|t:|1775724655\n|gametype|doubles\n|player|p1|San gerger|102|1352\n|player|p2|navinsachump|smasher|1418\n|gen|9\n|tier|[Gen 9] VGC 2026 Reg I\n|rated|\n|rule|Species Clause: Limit one of each Pok\u00e9mon\n|rule|Item Clause: Limit 1 of each item\n|clearpoke\n|poke|p1|Lunala, L50|\n|poke|p1|Miraidon, L50|\n|poke|p1|Whimsicott, L50, F|\n|poke|p1|Incineroar, L50, M|\n|poke|p1|Urshifu-*, L50, M|\n|poke|p1|Ursaluna, L50, M|\n|poke|p2|Miraidon, L50|\n|poke|p2|Incineroar, L50, M|\n|poke|p2|Whimsicott, L50, F|\n|poke|p2|Urshifu-*, L50, M|\n|poke|p2|Lunala, L50|\n|poke|p2|Ursaluna, L50, M|\n|teampreview|4\n|inactive|Battle timer is ON: inactive players will automatically lose when time's up. (requested by navinsachump)\n|inactive|San gerger has 60 seconds left.\n|inactive|navinsachump has 60 seconds left.\n|\n|t:|1775724702\n|teamsize|p1|4\n|teamsize|p2|4\n|start\n|switch|p1a: Lunala|Lunala, L50|100/100\n|switch|p1b: Miraidon|Miraidon, L50|100/100\n|switch|p2a: Lunala|Lunala, L50|100/100\n|switch|p2b: Incineroar|Incineroar, L50, M|100/100\n|-fieldstart|move: Electric Terrain|[from] ability: Hadron Engine|[of] p1b: Miraidon\n|-enditem|p1a: Lunala|Electric Seed\n|-boost|p1a: Lunala|def|1|[from] item: Electric Seed\n|-enditem|p2a: Lunala|Electric Seed\n|-boost|p2a: Lunala|def|1|[from] item: Electric Seed\n|-ability|p2b: Incineroar|Intimidate|boost\n|-unboost|p1a: Lunala|atk|1\n|-unboost|p1b: Miraidon|atk|1\n|turn|1\n|\n|t:|1775724726\n|-terastallize|p1a: Lunala|Fairy\n|-terastallize|p2a: Lunala|Fairy\n|move|p2b: Incineroar|Fake Out|p1b: Miraidon\n|-damage|p1b: Miraidon|88/100\n|cant|p1b: Miraidon|flinch\n|move|p1a: Lunala|Moongeist Beam|p2a: Lunala\n|-damage|p2a: Lunala|82/100\n|move|p2a: Lunala|Trick Room|p2a: Lunala\n|-fieldstart|move: Trick Room|[of] p2a: Lunala\n|\n|upkeep\n|turn|2\n|\n|t:|1775724749\n|move|p2b: Incineroar|U-turn|p1a: Lunala\n|-resisted|p1a: Lunala\n|-damage|p1a: Lunala|98/100\n|\n|t:|1775724752\n|switch|p2b: Ursaluna|Ursaluna, L50, M|100/100|[from] U-turn\n|move|p2a: Lunala|Moonblast|p1b: Miraidon\n|-supereffective|p1b: Miraidon\n|-damage|p1b: Miraidon|0 fnt\n|faint|p1b: Miraidon\n|move|p1a: Lunala|Moonblast|p2b: Ursaluna\n|-damage|p2b: Ursaluna|56/100\n|\n|-status|p2b: Ursaluna|brn|[from] item: Flame Orb\n|upkeep\n|\n|t:|1775724764\n|switch|p1b: Ursaluna|Ursaluna, L50, M|100/100\n|turn|3\n|\n|t:|1775724781\n|move|p1b: Ursaluna|Protect|p1b: Ursaluna\n|-singleturn|p1b: Ursaluna|Protect\n|move|p2b: Ursaluna|Facade|p1a: Lunala\n|-damage|p1a: Lunala|29/100\n|move|p2a: Lunala|Moongeist Beam|p1a: Lunala\n|-damage|p1a: Lunala|0 fnt\n|faint|p1a: Lunala\n|\n|-damage|p2b: Ursaluna|50/100 brn|[from] brn\n|-status|p1b: Ursaluna|brn|[from] item: Flame Orb\n|upkeep\n|-message|San gerger forfeited.\n|\n|win|navinsachump\n|raw|San gerger's rating: 1352 &rarr; <strong>1336</strong><br />(-16 for losing)\n|raw|navinsachump's rating: 1418 &rarr; <strong>1434</strong><br />(+16 for winning)\n|l|\u2606San gerger\n|player|p1|\n|l|\u2606navinsachump\n|player|p2|\n","uploadtime":1775725041,"views":9,"formatid":"gen9vgc2026regi","rating":1336,"private":0,"password":null}