{"id":"gen9vgc2026regi-2555826419","format":"[Gen 9] VGC 2026 Reg I","players":["Brick1014","hfyssgtslaaa"],"log":"|j|\u2606Brick1014\n|j|\u2606hfyssgtslaaa\n|t:|1773141974\n|gametype|doubles\n|player|p1|Brick1014|clair|1100\n|player|p2|hfyssgtslaaa|1|1166\n|gen|9\n|tier|[Gen 9] VGC 2026 Reg I\n|rated|\n|rule|Species Clause: Limit one of each Pok\u00e9mon\n|rule|Item Clause: Limit 1 of each item\n|clearpoke\n|poke|p1|Calyrex-Ice, L50|\n|poke|p1|Koraidon, L50|\n|poke|p1|Sandy Shocks, L50|\n|poke|p1|Murkrow, L50, M|\n|poke|p1|Entei, L50|\n|poke|p1|Cresselia, L50, F|\n|poke|p2|Raging Bolt, L50|\n|poke|p2|Chien-Pao, L50|\n|poke|p2|Calyrex-Shadow, L50|\n|poke|p2|Rillaboom, L50, M|\n|poke|p2|Amoonguss, L50, F|\n|poke|p2|Zamazenta-*, L50|\n|teampreview|4\n|\n|t:|1773142011\n|teamsize|p1|4\n|teamsize|p2|4\n|start\n|switch|p1a: Sandy Shocks|Sandy Shocks, L50|100/100\n|switch|p1b: Koraidon|Koraidon, L50|100/100\n|switch|p2a: Calyrex|Calyrex-Shadow, L50|100/100\n|switch|p2b: Zamazenta|Zamazenta-Crowned, L50|100/100\n|-ability|p2a: Calyrex|As One\n|-ability|p2a: Calyrex|Unnerve\n|-weather|SunnyDay|[from] ability: Orichalcum Pulse|[of] p1b: Koraidon\n|-activate|p1a: Sandy Shocks|ability: Protosynthesis\n|-start|p1a: Sandy Shocks|protosynthesisdef\n|-activate|p1b: Koraidon|Orichalcum Pulse|[source]\n|-ability|p2b: Zamazenta|Dauntless Shield|boost\n|-boost|p2b: Zamazenta|def|1\n|turn|1\n|\n|t:|1773142031\n|-terastallize|p1b: Koraidon|Fire\n|move|p2b: Zamazenta|Protect|p2b: Zamazenta\n|-singleturn|p2b: Zamazenta|Protect\n|move|p2a: Calyrex|Astral Barrage|p1b: Koraidon|[spread] p1a,p1b\n|-damage|p1a: Sandy Shocks|69/100\n|-damage|p1b: Koraidon|44/100\n|move|p1b: Koraidon|Flare Blitz|p2a: Calyrex\n|-enditem|p2a: Calyrex|Focus Sash\n|-damage|p2a: Calyrex|1/100\n|-damage|p1b: Koraidon|13/100|[from] Recoil\n|move|p1a: Sandy Shocks|Earth Power|p2b: Zamazenta\n|-activate|p2b: Zamazenta|move: Protect\n|\n|-weather|SunnyDay|[upkeep]\n|upkeep\n|turn|2\n|inactive|Battle timer is ON: inactive players will automatically lose when time's up. (requested by Brick1014)\n|\n|t:|1773142060\n|move|p1b: Koraidon|Protect|p1b: Koraidon\n|-singleturn|p1b: Koraidon|Protect\n|move|p2a: Calyrex|Astral Barrage|p1b: Koraidon|[spread] p1a\n|-activate|p1b: Koraidon|move: Protect\n|-damage|p1a: Sandy Shocks|37/100\n|move|p2b: Zamazenta|Body Press|p1a: Sandy Shocks\n|-damage|p1a: Sandy Shocks|0 fnt\n|faint|p1a: Sandy Shocks\n|-end|p1a: Sandy Shocks|Protosynthesis|[silent]\n|\n|-weather|SunnyDay|[upkeep]\n|upkeep\n|\n|t:|1773142072\n|switch|p1a: Murkrow|Murkrow, L50, M|100/100\n|turn|3\n|\n|t:|1773142085\n|-terastallize|p2b: Zamazenta|Water\n|move|p2a: Calyrex|Protect|p2a: Calyrex\n|-singleturn|p2a: Calyrex|Protect\n|move|p1a: Murkrow|Tailwind|p1a: Murkrow\n|-sidestart|p1: Brick1014|move: Tailwind\n|move|p1b: Koraidon|Collision Course|p2b: Zamazenta\n|-damage|p2b: Zamazenta|75/100\n|move|p2b: Zamazenta|Body Press|p1b: Koraidon\n|-damage|p1b: Koraidon|0 fnt\n|faint|p1b: Koraidon\n|\n|-weather|SunnyDay|[upkeep]\n|upkeep\n|l|\u2606Brick1014\n|inactive|Brick1014 disconnected and has a minute to reconnect!\n|player|p1|\n|inactive|Brick1014 has 30 seconds left.\n|inactive|Brick1014 has 20 seconds left.\n|inactive|Brick1014 has 15 seconds left.\n|inactive|Brick1014 has 10 seconds left.\n|inactive|Brick1014 has 5 seconds left.\n|-message|Brick1014 lost due to inactivity.\n|\n|win|hfyssgtslaaa\n|raw|Brick1014's rating: 1100 &rarr; <strong>1080</strong><br />(-20 for losing)\n|raw|hfyssgtslaaa's rating: 1166 &rarr; <strong>1186</strong><br />(+20 for winning)\n|l|\u2606hfyssgtslaaa\n|player|p2|\n","uploadtime":1773142543,"views":15,"formatid":"gen9vgc2026regi","rating":1080,"private":0,"password":null}